[
  {
    "feature": "Employee_Satisfaction_Score",
    "mean_abs_shap": 2.378634214401245,
    "rank": 1
  },
  {
    "feature": "Promotions",
    "mean_abs_shap": 0.8825544714927673,
    "rank": 2
  },
  {
    "feature": "Training_Hours",
    "mean_abs_shap": 0.7933909893035889,
    "rank": 3
  },
  {
    "feature": "Tenure_Performance_Ratio",
    "mean_abs_shap": 0.5943283438682556,
    "rank": 4
  },
  {
    "feature": "Work_Hours_Per_Week",
    "mean_abs_shap": 0.3771854043006897,
    "rank": 5
  },
  {
    "feature": "Workload_Intensity",
    "mean_abs_shap": 0.3568567633628845,
    "rank": 6
  },
  {
    "feature": "Performance_Score",
    "mean_abs_shap": 0.28096669912338257,
    "rank": 7
  },
  {
    "feature": "Projects_Handled",
    "mean_abs_shap": 0.15911580622196198,
    "rank": 8
  },
  {
    "feature": "Salary_Performance_Gap",
    "mean_abs_shap": 0.11488746851682663,
    "rank": 9
  },
  {
    "feature": "Sick_Days",
    "mean_abs_shap": 0.10901894420385361,
    "rank": 10
  },
  {
    "feature": "Burnout_Risk",
    "mean_abs_shap": 0.07219573110342026,
    "rank": 11
  },
  {
    "feature": "Is_Underutilized",
    "mean_abs_shap": 0.07180941849946976,
    "rank": 12
  },
  {
    "feature": "Training_Per_Year",
    "mean_abs_shap": 0.0688302218914032,
    "rank": 13
  },
  {
    "feature": "Project_Load",
    "mean_abs_shap": 0.0594278909265995,
    "rank": 14
  },
  {
    "feature": "Monthly_Salary",
    "mean_abs_shap": 0.056435760110616684,
    "rank": 15
  },
  {
    "feature": "Work_Life_Balance",
    "mean_abs_shap": 0.0497262142598629,
    "rank": 16
  },
  {
    "feature": "Overtime_Ratio",
    "mean_abs_shap": 0.010889312252402306,
    "rank": 17
  },
  {
    "feature": "Overtime_Hours",
    "mean_abs_shap": 0.010337535291910172,
    "rank": 18
  },
  {
    "feature": "Age",
    "mean_abs_shap": 0.009518396109342575,
    "rank": 19
  },
  {
    "feature": "Is_Overworked",
    "mean_abs_shap": 0.004420125391334295,
    "rank": 20
  }
]